odoo/addons/mgmtsystem_nonconformity_hr/README.rst
odoo/addons/mgmtsystem_nonconformity_hr/__init__.py
odoo/addons/mgmtsystem_nonconformity_hr/__manifest__.py
odoo/addons/mgmtsystem_nonconformity_hr/i18n/es.po
odoo/addons/mgmtsystem_nonconformity_hr/i18n/fa.po
odoo/addons/mgmtsystem_nonconformity_hr/i18n/fr.po
odoo/addons/mgmtsystem_nonconformity_hr/i18n/it.po
odoo/addons/mgmtsystem_nonconformity_hr/i18n/mgmtsystem_nonconformity_hr.pot
odoo/addons/mgmtsystem_nonconformity_hr/i18n/pt.po
odoo/addons/mgmtsystem_nonconformity_hr/models/__init__.py
odoo/addons/mgmtsystem_nonconformity_hr/models/mgmtsystem_nonconformity_hr.py
odoo/addons/mgmtsystem_nonconformity_hr/readme/CONTRIBUTORS.md
odoo/addons/mgmtsystem_nonconformity_hr/readme/DESCRIPTION.md
odoo/addons/mgmtsystem_nonconformity_hr/readme/HISTORY.md
odoo/addons/mgmtsystem_nonconformity_hr/readme/USAGE.md
odoo/addons/mgmtsystem_nonconformity_hr/static/description/icon.png
odoo/addons/mgmtsystem_nonconformity_hr/static/description/index.html
odoo/addons/mgmtsystem_nonconformity_hr/views/mgmtsystem_nonconformity_views.xml
odoo_addon_mgmtsystem_nonconformity_hr-18.0.1.0.0.2.dist-info/METADATA
odoo_addon_mgmtsystem_nonconformity_hr-18.0.1.0.0.2.dist-info/WHEEL
odoo_addon_mgmtsystem_nonconformity_hr-18.0.1.0.0.2.dist-info/top_level.txt
odoo_addon_mgmtsystem_nonconformity_hr-18.0.1.0.0.2.dist-info/RECORD
