Metadata-Version: 2.1
Name: odoo-addon-mgmtsystem_nonconformity_hr
Version: 18.0.1.0.0.2
Requires-Python: >=3.10
Requires-Dist: odoo-addon-mgmtsystem_nonconformity==18.0.*
Requires-Dist: odoo==18.0.*
Summary: Bridge module between hr and mgmsystem and
Home-page: https://github.com/OCA/management-system
License: AGPL-3
Author: Associazione PNLUG - Gruppo Odoo, Odoo Community Association (OCA)
Author-email: support@odoo-community.org
Classifier: Programming Language :: Python
Classifier: Framework :: Odoo
Classifier: Framework :: Odoo :: 18.0
Classifier: License :: OSI Approved :: GNU Affero General Public License v3
